anthropic_zeusdb/__init__.py
anthropic_zeusdb-0.0.0.dist-info/METADATA
anthropic_zeusdb-0.0.0.dist-info/WHEEL
anthropic_zeusdb-0.0.0.dist-info/top_level.txt
anthropic_zeusdb-0.0.0.dist-info/RECORD
