Metadata-Version: 2.4
Name: anthropic-zeusdb
Version: 0.0.0
Summary: Enterprise-grade RAG with Claude: Anthropic's reasoning AI + ZeusDB's high-performance vector storage with built-in safety.
